electrodb/__init__.py
electrodb/branch.py
electrodb-1.0.1.dist-info/LICENSE
electrodb-1.0.1.dist-info/METADATA
electrodb-1.0.1.dist-info/WHEEL
electrodb-1.0.1.dist-info/top_level.txt
electrodb-1.0.1.dist-info/RECORD
