Metadata-Version: 2.1
Name: electrodb
Version: 1.0.1
Summary: This project provides a reliable database, allowing you to perform CRUD operations and more on collections of documents.
Home-page: https://github.com/E491K8/electrodb
Author: Pawan kumar
Author-email: confict.con@gmail.com
Keywords: your,keywords,here
Classifier: Development Status :: 3 - Alpha
Classifier: Intended Audience :: Developers
Classifier: Topic :: Software Development :: Libraries
Classifier: License :: OSI Approved :: MIT License
Classifier: Programming Language :: Python :: 3
Classifier: Programming Language :: Python :: 3.6
Classifier: Programming Language :: Python :: 3.7
Classifier: Programming Language :: Python :: 3.8
Classifier: Programming Language :: Python :: 3.9
Requires-Python: >=3.6
License-File: LICENSE
Requires-Dist: requests
Requires-Dist: bson
